bibdesk2zotero
