Metadata-Version: 2.1
Name: bibdesk2zotero
Version: 0.0.2
Summary: convert BibDesk BibTeX files for import into Zotero
Home-page: https://github.com/edsu/bibdesk2zotero
Author: Ed Summers
Author-email: ehs@pobox.com
License: UNKNOWN
Platform: UNKNOWN
